{
  "type": "File",
  "start": 0,
  "end": 707,
  "loc": {
    "start": {
      "line": 1,
      "column": 0
    },
    "end": {
      "line": 22,
      "column": 0
    }
  },
  "program": {
    "type": "Program",
    "start": 0,
    "end": 707,
    "loc": {
      "start": {
        "line": 1,
        "column": 0
      },
      "end": {
        "line": 22,
        "column": 0
      }
    },
    "sourceType": "module",
    "body": [
      {
        "type": "ExportNamedDeclaration",
        "start": 15,
        "end": 62,
        "loc": {
          "start": {
            "line": 3,
            "column": 0
          },
          "end": {
            "line": 3,
            "column": 47
          }
        },
        "declaration": null,
        "specifiers": [
          {
            "type": "ExportSpecifier",
            "start": 23,
            "end": 42,
            "loc": {
              "start": {
                "line": 3,
                "column": 8
              },
              "end": {
                "line": 3,
                "column": 27
              }
            },
            "local": {
              "type": "Identifier",
              "start": 23,
              "end": 30,
              "loc": {
                "start": {
                  "line": 3,
                  "column": 8
                },
                "end": {
                  "line": 3,
                  "column": 15
                },
                "identifierName": "default"
              },
              "name": "default"
            },
            "exported": {
              "type": "Identifier",
              "start": 34,
              "end": 42,
              "loc": {
                "start": {
                  "line": 3,
                  "column": 19
                },
                "end": {
                  "line": 3,
                  "column": 27
                },
                "identifierName": "Timeline"
              },
              "name": "Timeline"
            }
          }
        ],
        "source": {
          "type": "StringLiteral",
          "start": 49,
          "end": 61,
          "loc": {
            "start": {
              "line": 3,
              "column": 34
            },
            "end": {
              "line": 3,
              "column": 46
            }
          },
          "extra": {
            "rawValue": "./timeline",
            "raw": "'./timeline'"
          },
          "value": "./timeline"
        }
      },
      {
        "type": "ExportAllDeclaration",
        "start": 63,
        "end": 87,
        "loc": {
          "start": {
            "line": 4,
            "column": 0
          },
          "end": {
            "line": 4,
            "column": 24
          }
        },
        "source": {
          "type": "StringLiteral",
          "start": 77,
          "end": 86,
          "loc": {
            "start": {
              "line": 4,
              "column": 14
            },
            "end": {
              "line": 4,
              "column": 23
            }
          },
          "extra": {
            "rawValue": "./types",
            "raw": "'./types'"
          },
          "value": "./types"
        },
        "trailingComments": [
          {
            "type": "CommentLine",
            "value": " components",
            "start": 89,
            "end": 102,
            "loc": {
              "start": {
                "line": 6,
                "column": 0
              },
              "end": {
                "line": 6,
                "column": 13
              }
            }
          }
        ]
      },
      {
        "type": "ExportNamedDeclaration",
        "start": 103,
        "end": 159,
        "loc": {
          "start": {
            "line": 7,
            "column": 0
          },
          "end": {
            "line": 7,
            "column": 56
          }
        },
        "declaration": null,
        "specifiers": [
          {
            "type": "ExportSpecifier",
            "start": 111,
            "end": 129,
            "loc": {
              "start": {
                "line": 7,
                "column": 8
              },
              "end": {
                "line": 7,
                "column": 26
              }
            },
            "local": {
              "type": "Identifier",
              "start": 111,
              "end": 118,
              "loc": {
                "start": {
                  "line": 7,
                  "column": 8
                },
                "end": {
                  "line": 7,
                  "column": 15
                },
                "identifierName": "default"
              },
              "name": "default",
              "leadingComments": null
            },
            "exported": {
              "type": "Identifier",
              "start": 122,
              "end": 129,
              "loc": {
                "start": {
                  "line": 7,
                  "column": 19
                },
                "end": {
                  "line": 7,
                  "column": 26
                },
                "identifierName": "Timebar"
              },
              "name": "Timebar"
            },
            "leadingComments": null
          }
        ],
        "source": {
          "type": "StringLiteral",
          "start": 136,
          "end": 158,
          "loc": {
            "start": {
              "line": 7,
              "column": 33
            },
            "end": {
              "line": 7,
              "column": 55
            }
          },
          "extra": {
            "rawValue": "./components/timebar",
            "raw": "'./components/timebar'"
          },
          "value": "./components/timebar"
        },
        "leadingComments": [
          {
            "type": "CommentLine",
            "value": " components",
            "start": 89,
            "end": 102,
            "loc": {
              "start": {
                "line": 6,
                "column": 0
              },
              "end": {
                "line": 6,
                "column": 13
              }
            }
          }
        ]
      },
      {
        "type": "ExportNamedDeclaration",
        "start": 160,
        "end": 218,
        "loc": {
          "start": {
            "line": 8,
            "column": 0
          },
          "end": {
            "line": 8,
            "column": 58
          }
        },
        "declaration": null,
        "specifiers": [
          {
            "type": "ExportSpecifier",
            "start": 168,
            "end": 191,
            "loc": {
              "start": {
                "line": 8,
                "column": 8
              },
              "end": {
                "line": 8,
                "column": 31
              }
            },
            "local": {
              "type": "Identifier",
              "start": 168,
              "end": 175,
              "loc": {
                "start": {
                  "line": 8,
                  "column": 8
                },
                "end": {
                  "line": 8,
                  "column": 15
                },
                "identifierName": "default"
              },
              "name": "default"
            },
            "exported": {
              "type": "Identifier",
              "start": 179,
              "end": 191,
              "loc": {
                "start": {
                  "line": 8,
                  "column": 19
                },
                "end": {
                  "line": 8,
                  "column": 31
                },
                "identifierName": "TimelineBody"
              },
              "name": "TimelineBody"
            }
          }
        ],
        "source": {
          "type": "StringLiteral",
          "start": 198,
          "end": 217,
          "loc": {
            "start": {
              "line": 8,
              "column": 38
            },
            "end": {
              "line": 8,
              "column": 57
            }
          },
          "extra": {
            "rawValue": "./components/body",
            "raw": "'./components/body'"
          },
          "value": "./components/body"
        }
      },
      {
        "type": "ExportNamedDeclaration",
        "start": 219,
        "end": 285,
        "loc": {
          "start": {
            "line": 9,
            "column": 0
          },
          "end": {
            "line": 9,
            "column": 66
          }
        },
        "declaration": null,
        "specifiers": [
          {
            "type": "ExportSpecifier",
            "start": 227,
            "end": 250,
            "loc": {
              "start": {
                "line": 9,
                "column": 8
              },
              "end": {
                "line": 9,
                "column": 31
              }
            },
            "local": {
              "type": "Identifier",
              "start": 227,
              "end": 234,
              "loc": {
                "start": {
                  "line": 9,
                  "column": 8
                },
                "end": {
                  "line": 9,
                  "column": 15
                },
                "identifierName": "default"
              },
              "name": "default"
            },
            "exported": {
              "type": "Identifier",
              "start": 238,
              "end": 250,
              "loc": {
                "start": {
                  "line": 9,
                  "column": 19
                },
                "end": {
                  "line": 9,
                  "column": 31
                },
                "identifierName": "ItemRenderer"
              },
              "name": "ItemRenderer"
            }
          }
        ],
        "source": {
          "type": "StringLiteral",
          "start": 257,
          "end": 284,
          "loc": {
            "start": {
              "line": 9,
              "column": 38
            },
            "end": {
              "line": 9,
              "column": 65
            }
          },
          "extra": {
            "rawValue": "./components/ItemRenderer",
            "raw": "'./components/ItemRenderer'"
          },
          "value": "./components/ItemRenderer"
        }
      },
      {
        "type": "ExportNamedDeclaration",
        "start": 286,
        "end": 343,
        "loc": {
          "start": {
            "line": 10,
            "column": 0
          },
          "end": {
            "line": 10,
            "column": 57
          }
        },
        "declaration": null,
        "specifiers": [
          {
            "type": "ExportSpecifier",
            "start": 294,
            "end": 307,
            "loc": {
              "start": {
                "line": 10,
                "column": 8
              },
              "end": {
                "line": 10,
                "column": 21
              }
            },
            "local": {
              "type": "Identifier",
              "start": 294,
              "end": 307,
              "loc": {
                "start": {
                  "line": 10,
                  "column": 8
                },
                "end": {
                  "line": 10,
                  "column": 21
                },
                "identifierName": "GroupRenderer"
              },
              "name": "GroupRenderer"
            },
            "exported": {
              "type": "Identifier",
              "start": 294,
              "end": 307,
              "loc": {
                "start": {
                  "line": 10,
                  "column": 8
                },
                "end": {
                  "line": 10,
                  "column": 21
                },
                "identifierName": "GroupRenderer"
              },
              "name": "GroupRenderer"
            }
          }
        ],
        "source": {
          "type": "StringLiteral",
          "start": 314,
          "end": 342,
          "loc": {
            "start": {
              "line": 10,
              "column": 28
            },
            "end": {
              "line": 10,
              "column": 56
            }
          },
          "extra": {
            "rawValue": "./components/GroupRenderer",
            "raw": "'./components/GroupRenderer'"
          },
          "value": "./components/GroupRenderer"
        }
      },
      {
        "type": "ExportNamedDeclaration",
        "start": 344,
        "end": 409,
        "loc": {
          "start": {
            "line": 11,
            "column": 0
          },
          "end": {
            "line": 11,
            "column": 65
          }
        },
        "declaration": null,
        "specifiers": [
          {
            "type": "ExportSpecifier",
            "start": 352,
            "end": 372,
            "loc": {
              "start": {
                "line": 11,
                "column": 8
              },
              "end": {
                "line": 11,
                "column": 28
              }
            },
            "local": {
              "type": "Identifier",
              "start": 352,
              "end": 372,
              "loc": {
                "start": {
                  "line": 11,
                  "column": 8
                },
                "end": {
                  "line": 11,
                  "column": 28
                },
                "identifierName": "ColumnHeaderRenderer"
              },
              "name": "ColumnHeaderRenderer"
            },
            "exported": {
              "type": "Identifier",
              "start": 352,
              "end": 372,
              "loc": {
                "start": {
                  "line": 11,
                  "column": 8
                },
                "end": {
                  "line": 11,
                  "column": 28
                },
                "identifierName": "ColumnHeaderRenderer"
              },
              "name": "ColumnHeaderRenderer"
            }
          }
        ],
        "source": {
          "type": "StringLiteral",
          "start": 379,
          "end": 408,
          "loc": {
            "start": {
              "line": 11,
              "column": 35
            },
            "end": {
              "line": 11,
              "column": 64
            }
          },
          "extra": {
            "rawValue": "./components/ColumnRenderer",
            "raw": "'./components/ColumnRenderer'"
          },
          "value": "./components/ColumnRenderer"
        }
      },
      {
        "type": "ExportNamedDeclaration",
        "start": 410,
        "end": 464,
        "loc": {
          "start": {
            "line": 12,
            "column": 0
          },
          "end": {
            "line": 12,
            "column": 54
          }
        },
        "declaration": null,
        "specifiers": [
          {
            "type": "ExportSpecifier",
            "start": 418,
            "end": 435,
            "loc": {
              "start": {
                "line": 12,
                "column": 8
              },
              "end": {
                "line": 12,
                "column": 25
              }
            },
            "local": {
              "type": "Identifier",
              "start": 418,
              "end": 425,
              "loc": {
                "start": {
                  "line": 12,
                  "column": 8
                },
                "end": {
                  "line": 12,
                  "column": 15
                },
                "identifierName": "default"
              },
              "name": "default"
            },
            "exported": {
              "type": "Identifier",
              "start": 429,
              "end": 435,
              "loc": {
                "start": {
                  "line": 12,
                  "column": 19
                },
                "end": {
                  "line": 12,
                  "column": 25
                },
                "identifierName": "Marker"
              },
              "name": "Marker"
            }
          }
        ],
        "source": {
          "type": "StringLiteral",
          "start": 442,
          "end": 463,
          "loc": {
            "start": {
              "line": 12,
              "column": 32
            },
            "end": {
              "line": 12,
              "column": 53
            }
          },
          "extra": {
            "rawValue": "./components/marker",
            "raw": "'./components/marker'"
          },
          "value": "./components/marker"
        }
      },
      {
        "type": "ExportNamedDeclaration",
        "start": 465,
        "end": 524,
        "loc": {
          "start": {
            "line": 13,
            "column": 0
          },
          "end": {
            "line": 13,
            "column": 59
          }
        },
        "declaration": null,
        "specifiers": [
          {
            "type": "ExportSpecifier",
            "start": 473,
            "end": 493,
            "loc": {
              "start": {
                "line": 13,
                "column": 8
              },
              "end": {
                "line": 13,
                "column": 28
              }
            },
            "local": {
              "type": "Identifier",
              "start": 473,
              "end": 480,
              "loc": {
                "start": {
                  "line": 13,
                  "column": 8
                },
                "end": {
                  "line": 13,
                  "column": 15
                },
                "identifierName": "default"
              },
              "name": "default"
            },
            "exported": {
              "type": "Identifier",
              "start": 484,
              "end": 493,
              "loc": {
                "start": {
                  "line": 13,
                  "column": 19
                },
                "end": {
                  "line": 13,
                  "column": 28
                },
                "identifierName": "Selectbox"
              },
              "name": "Selectbox"
            }
          }
        ],
        "source": {
          "type": "StringLiteral",
          "start": 500,
          "end": 523,
          "loc": {
            "start": {
              "line": 13,
              "column": 35
            },
            "end": {
              "line": 13,
              "column": 58
            }
          },
          "extra": {
            "rawValue": "./components/selector",
            "raw": "'./components/selector'"
          },
          "value": "./components/selector"
        },
        "trailingComments": [
          {
            "type": "CommentLine",
            "value": " consts",
            "start": 526,
            "end": 535,
            "loc": {
              "start": {
                "line": 15,
                "column": 0
              },
              "end": {
                "line": 15,
                "column": 9
              }
            }
          }
        ]
      },
      {
        "type": "ExportNamedDeclaration",
        "start": 536,
        "end": 589,
        "loc": {
          "start": {
            "line": 16,
            "column": 0
          },
          "end": {
            "line": 16,
            "column": 53
          }
        },
        "declaration": null,
        "specifiers": [
          {
            "type": "ExportSpecifier",
            "start": 544,
            "end": 557,
            "loc": {
              "start": {
                "line": 16,
                "column": 8
              },
              "end": {
                "line": 16,
                "column": 21
              }
            },
            "local": {
              "type": "Identifier",
              "start": 544,
              "end": 557,
              "loc": {
                "start": {
                  "line": 16,
                  "column": 8
                },
                "end": {
                  "line": 16,
                  "column": 21
                },
                "identifierName": "timebarFormat"
              },
              "name": "timebarFormat",
              "leadingComments": null
            },
            "exported": {
              "type": "Identifier",
              "start": 544,
              "end": 557,
              "loc": {
                "start": {
                  "line": 16,
                  "column": 8
                },
                "end": {
                  "line": 16,
                  "column": 21
                },
                "identifierName": "timebarFormat"
              },
              "name": "timebarFormat"
            },
            "leadingComments": null
          }
        ],
        "source": {
          "type": "StringLiteral",
          "start": 564,
          "end": 588,
          "loc": {
            "start": {
              "line": 16,
              "column": 28
            },
            "end": {
              "line": 16,
              "column": 52
            }
          },
          "extra": {
            "rawValue": "./consts/timebarConsts",
            "raw": "'./consts/timebarConsts'"
          },
          "value": "./consts/timebarConsts"
        },
        "leadingComments": [
          {
            "type": "CommentLine",
            "value": " consts",
            "start": 526,
            "end": 535,
            "loc": {
              "start": {
                "line": 15,
                "column": 0
              },
              "end": {
                "line": 15,
                "column": 9
              }
            }
          }
        ],
        "trailingComments": [
          {
            "type": "CommentLine",
            "value": " utils",
            "start": 591,
            "end": 599,
            "loc": {
              "start": {
                "line": 18,
                "column": 0
              },
              "end": {
                "line": 18,
                "column": 8
              }
            }
          }
        ]
      },
      {
        "type": "ExportAllDeclaration",
        "start": 600,
        "end": 636,
        "loc": {
          "start": {
            "line": 19,
            "column": 0
          },
          "end": {
            "line": 19,
            "column": 36
          }
        },
        "source": {
          "type": "StringLiteral",
          "start": 614,
          "end": 635,
          "loc": {
            "start": {
              "line": 19,
              "column": 14
            },
            "end": {
              "line": 19,
              "column": 35
            }
          },
          "extra": {
            "rawValue": "./utils/commonUtils",
            "raw": "'./utils/commonUtils'"
          },
          "value": "./utils/commonUtils",
          "leadingComments": null
        },
        "leadingComments": [
          {
            "type": "CommentLine",
            "value": " utils",
            "start": 591,
            "end": 599,
            "loc": {
              "start": {
                "line": 18,
                "column": 0
              },
              "end": {
                "line": 18,
                "column": 8
              }
            }
          }
        ]
      },
      {
        "type": "ExportAllDeclaration",
        "start": 637,
        "end": 671,
        "loc": {
          "start": {
            "line": 20,
            "column": 0
          },
          "end": {
            "line": 20,
            "column": 34
          }
        },
        "source": {
          "type": "StringLiteral",
          "start": 651,
          "end": 670,
          "loc": {
            "start": {
              "line": 20,
              "column": 14
            },
            "end": {
              "line": 20,
              "column": 33
            }
          },
          "extra": {
            "rawValue": "./utils/itemUtils",
            "raw": "'./utils/itemUtils'"
          },
          "value": "./utils/itemUtils"
        }
      },
      {
        "type": "ExportAllDeclaration",
        "start": 672,
        "end": 706,
        "loc": {
          "start": {
            "line": 21,
            "column": 0
          },
          "end": {
            "line": 21,
            "column": 34
          }
        },
        "source": {
          "type": "StringLiteral",
          "start": 686,
          "end": 705,
          "loc": {
            "start": {
              "line": 21,
              "column": 14
            },
            "end": {
              "line": 21,
              "column": 33
            }
          },
          "extra": {
            "rawValue": "./utils/timeUtils",
            "raw": "'./utils/timeUtils'"
          },
          "value": "./utils/timeUtils"
        }
      }
    ],
    "directives": [
      {
        "type": "Directive",
        "start": 0,
        "end": 13,
        "loc": {
          "start": {
            "line": 1,
            "column": 0
          },
          "end": {
            "line": 1,
            "column": 13
          }
        },
        "value": {
          "type": "DirectiveLiteral",
          "start": 0,
          "end": 12,
          "loc": {
            "start": {
              "line": 1,
              "column": 0
            },
            "end": {
              "line": 1,
              "column": 12
            }
          },
          "value": "use strict",
          "extra": {
            "raw": "'use strict'",
            "rawValue": "use strict"
          }
        }
      }
    ]
  },
  "comments": [
    {
      "type": "CommentLine",
      "value": " components",
      "start": 89,
      "end": 102,
      "loc": {
        "start": {
          "line": 6,
          "column": 0
        },
        "end": {
          "line": 6,
          "column": 13
        }
      }
    },
    {
      "type": "CommentLine",
      "value": " consts",
      "start": 526,
      "end": 535,
      "loc": {
        "start": {
          "line": 15,
          "column": 0
        },
        "end": {
          "line": 15,
          "column": 9
        }
      }
    },
    {
      "type": "CommentLine",
      "value": " utils",
      "start": 591,
      "end": 599,
      "loc": {
        "start": {
          "line": 18,
          "column": 0
        },
        "end": {
          "line": 18,
          "column": 8
        }
      }
    }
  ],
  "tokens": [
    {
      "type": {
        "label": "string",
        "beforeExpr": false,
        "startsExpr": true,
        "rightAssociative": false,
        "isLoop": false,
        "isAssign": false,
        "prefix": false,
        "postfix": false,
        "binop": null,
        "updateContext": null
      },
      "value": "use strict",
      "start": 0,
      "end": 12,
      "loc": {
        "start": {
          "line": 1,
          "column": 0
        },
        "end": {
          "line": 1,
          "column": 12
        }
      }
    },
    {
      "type": {
        "label": ";",
        "beforeExpr": true,
        "startsExpr": false,
        "rightAssociative": false,
        "isLoop": false,
        "isAssign": false,
        "prefix": false,
        "postfix": false,
        "binop": null,
        "updateContext": null
      },
      "start": 12,
      "end": 13,
      "loc": {
        "start": {
          "line": 1,
          "column": 12
        },
        "end": {
          "line": 1,
          "column": 13
        }
      }
    },
    {
      "type": {
        "label": "export",
        "keyword": "export",
        "beforeExpr": false,
        "startsExpr": false,
        "rightAssociative": false,
        "isLoop": false,
        "isAssign": false,
        "prefix": false,
        "postfix": false,
        "binop": null,
        "updateContext": null
      },
      "value": "export",
      "start": 15,
      "end": 21,
      "loc": {
        "start": {
          "line": 3,
          "column": 0
        },
        "end": {
          "line": 3,
          "column": 6
        }
      }
    },
    {
      "type": {
        "label": "{",
        "beforeExpr": true,
        "startsExpr": true,
        "rightAssociative": false,
        "isLoop": false,
        "isAssign": false,
        "prefix": false,
        "postfix": false,
        "binop": null
      },
      "start": 22,
      "end": 23,
      "loc": {
        "start": {
          "line": 3,
          "column": 7
        },
        "end": {
          "line": 3,
          "column": 8
        }
      }
    },
    {
      "type": {
        "label": "default",
        "keyword": "default",
        "beforeExpr": true,
        "startsExpr": false,
        "rightAssociative": false,
        "isLoop": false,
        "isAssign": false,
        "prefix": false,
        "postfix": false,
        "binop": null,
        "updateContext": null
      },
      "value": "default",
      "start": 23,
      "end": 30,
      "loc": {
        "start": {
          "line": 3,
          "column": 8
        },
        "end": {
          "line": 3,
          "column": 15
        }
      }
    },
    {
      "type": {
        "label": "name",
        "beforeExpr": false,
        "startsExpr": true,
        "rightAssociative": false,
        "isLoop": false,
        "isAssign": false,
        "prefix": false,
        "postfix": false,
        "binop": null
      },
      "value": "as",
      "start": 31,
      "end": 33,
      "loc": {
        "start": {
          "line": 3,
          "column": 16
        },
        "end": {
          "line": 3,
          "column": 18
        }
      }
    },
    {
      "type": {
        "label": "name",
        "beforeExpr": false,
        "startsExpr": true,
        "rightAssociative": false,
        "isLoop": false,
        "isAssign": false,
        "prefix": false,
        "postfix": false,
        "binop": null
      },
      "value": "Timeline",
      "start": 34,
      "end": 42,
      "loc": {
        "start": {
          "line": 3,
          "column": 19
        },
        "end": {
          "line": 3,
          "column": 27
        }
      }
    },
    {
      "type": {
        "label": "}",
        "beforeExpr": false,
        "startsExpr": false,
        "rightAssociative": false,
        "isLoop": false,
        "isAssign": false,
        "prefix": false,
        "postfix": false,
        "binop": null
      },
      "start": 42,
      "end": 43,
      "loc": {
        "start": {
          "line": 3,
          "column": 27
        },
        "end": {
          "line": 3,
          "column": 28
        }
      }
    },
    {
      "type": {
        "label": "name",
        "beforeExpr": false,
        "startsExpr": true,
        "rightAssociative": false,
        "isLoop": false,
        "isAssign": false,
        "prefix": false,
        "postfix": false,
        "binop": null
      },
      "value": "from",
      "start": 44,
      "end": 48,
      "loc": {
        "start": {
          "line": 3,
          "column": 29
        },
        "end": {
          "line": 3,
          "column": 33
        }
      }
    },
    {
      "type": {
        "label": "string",
        "beforeExpr": false,
        "startsExpr": true,
        "rightAssociative": false,
        "isLoop": false,
        "isAssign": false,
        "prefix": false,
        "postfix": false,
        "binop": null,
        "updateContext": null
      },
      "value": "./timeline",
      "start": 49,
      "end": 61,
      "loc": {
        "start": {
          "line": 3,
          "column": 34
        },
        "end": {
          "line": 3,
          "column": 46
        }
      }
    },
    {
      "type": {
        "label": ";",
        "beforeExpr": true,
        "startsExpr": false,
        "rightAssociative": false,
        "isLoop": false,
        "isAssign": false,
        "prefix": false,
        "postfix": false,
        "binop": null,
        "updateContext": null
      },
      "start": 61,
      "end": 62,
      "loc": {
        "start": {
          "line": 3,
          "column": 46
        },
        "end": {
          "line": 3,
          "column": 47
        }
      }
    },
    {
      "type": {
        "label": "export",
        "keyword": "export",
        "beforeExpr": false,
        "startsExpr": false,
        "rightAssociative": false,
        "isLoop": false,
        "isAssign": false,
        "prefix": false,
        "postfix": false,
        "binop": null,
        "updateContext": null
      },
      "value": "export",
      "start": 63,
      "end": 69,
      "loc": {
        "start": {
          "line": 4,
          "column": 0
        },
        "end": {
          "line": 4,
          "column": 6
        }
      }
    },
    {
      "type": {
        "label": "*",
        "beforeExpr": true,
        "startsExpr": false,
        "rightAssociative": false,
        "isLoop": false,
        "isAssign": false,
        "prefix": false,
        "postfix": false,
        "binop": 10,
        "updateContext": null
      },
      "value": "*",
      "start": 70,
      "end": 71,
      "loc": {
        "start": {
          "line": 4,
          "column": 7
        },
        "end": {
          "line": 4,
          "column": 8
        }
      }
    },
    {
      "type": {
        "label": "name",
        "beforeExpr": false,
        "startsExpr": true,
        "rightAssociative": false,
        "isLoop": false,
        "isAssign": false,
        "prefix": false,
        "postfix": false,
        "binop": null
      },
      "value": "from",
      "start": 72,
      "end": 76,
      "loc": {
        "start": {
          "line": 4,
          "column": 9
        },
        "end": {
          "line": 4,
          "column": 13
        }
      }
    },
    {
      "type": {
        "label": "string",
        "beforeExpr": false,
        "startsExpr": true,
        "rightAssociative": false,
        "isLoop": false,
        "isAssign": false,
        "prefix": false,
        "postfix": false,
        "binop": null,
        "updateContext": null
      },
      "value": "./types",
      "start": 77,
      "end": 86,
      "loc": {
        "start": {
          "line": 4,
          "column": 14
        },
        "end": {
          "line": 4,
          "column": 23
        }
      }
    },
    {
      "type": {
        "label": ";",
        "beforeExpr": true,
        "startsExpr": false,
        "rightAssociative": false,
        "isLoop": false,
        "isAssign": false,
        "prefix": false,
        "postfix": false,
        "binop": null,
        "updateContext": null
      },
      "start": 86,
      "end": 87,
      "loc": {
        "start": {
          "line": 4,
          "column": 23
        },
        "end": {
          "line": 4,
          "column": 24
        }
      }
    },
    {
      "type": "CommentLine",
      "value": " components",
      "start": 89,
      "end": 102,
      "loc": {
        "start": {
          "line": 6,
          "column": 0
        },
        "end": {
          "line": 6,
          "column": 13
        }
      }
    },
    {
      "type": {
        "label": "export",
        "keyword": "export",
        "beforeExpr": false,
        "startsExpr": false,
        "rightAssociative": false,
        "isLoop": false,
        "isAssign": false,
        "prefix": false,
        "postfix": false,
        "binop": null,
        "updateContext": null
      },
      "value": "export",
      "start": 103,
      "end": 109,
      "loc": {
        "start": {
          "line": 7,
          "column": 0
        },
        "end": {
          "line": 7,
          "column": 6
        }
      }
    },
    {
      "type": {
        "label": "{",
        "beforeExpr": true,
        "startsExpr": true,
        "rightAssociative": false,
        "isLoop": false,
        "isAssign": false,
        "prefix": false,
        "postfix": false,
        "binop": null
      },
      "start": 110,
      "end": 111,
      "loc": {
        "start": {
          "line": 7,
          "column": 7
        },
        "end": {
          "line": 7,
          "column": 8
        }
      }
    },
    {
      "type": {
        "label": "default",
        "keyword": "default",
        "beforeExpr": true,
        "startsExpr": false,
        "rightAssociative": false,
        "isLoop": false,
        "isAssign": false,
        "prefix": false,
        "postfix": false,
        "binop": null,
        "updateContext": null
      },
      "value": "default",
      "start": 111,
      "end": 118,
      "loc": {
        "start": {
          "line": 7,
          "column": 8
        },
        "end": {
          "line": 7,
          "column": 15
        }
      }
    },
    {
      "type": {
        "label": "name",
        "beforeExpr": false,
        "startsExpr": true,
        "rightAssociative": false,
        "isLoop": false,
        "isAssign": false,
        "prefix": false,
        "postfix": false,
        "binop": null
      },
      "value": "as",
      "start": 119,
      "end": 121,
      "loc": {
        "start": {
          "line": 7,
          "column": 16
        },
        "end": {
          "line": 7,
          "column": 18
        }
      }
    },
    {
      "type": {
        "label": "name",
        "beforeExpr": false,
        "startsExpr": true,
        "rightAssociative": false,
        "isLoop": false,
        "isAssign": false,
        "prefix": false,
        "postfix": false,
        "binop": null
      },
      "value": "Timebar",
      "start": 122,
      "end": 129,
      "loc": {
        "start": {
          "line": 7,
          "column": 19
        },
        "end": {
          "line": 7,
          "column": 26
        }
      }
    },
    {
      "type": {
        "label": "}",
        "beforeExpr": false,
        "startsExpr": false,
        "rightAssociative": false,
        "isLoop": false,
        "isAssign": false,
        "prefix": false,
        "postfix": false,
        "binop": null
      },
      "start": 129,
      "end": 130,
      "loc": {
        "start": {
          "line": 7,
          "column": 26
        },
        "end": {
          "line": 7,
          "column": 27
        }
      }
    },
    {
      "type": {
        "label": "name",
        "beforeExpr": false,
        "startsExpr": true,
        "rightAssociative": false,
        "isLoop": false,
        "isAssign": false,
        "prefix": false,
        "postfix": false,
        "binop": null
      },
      "value": "from",
      "start": 131,
      "end": 135,
      "loc": {
        "start": {
          "line": 7,
          "column": 28
        },
        "end": {
          "line": 7,
          "column": 32
        }
      }
    },
    {
      "type": {
        "label": "string",
        "beforeExpr": false,
        "startsExpr": true,
        "rightAssociative": false,
        "isLoop": false,
        "isAssign": false,
        "prefix": false,
        "postfix": false,
        "binop": null,
        "updateContext": null
      },
      "value": "./components/timebar",
      "start": 136,
      "end": 158,
      "loc": {
        "start": {
          "line": 7,
          "column": 33
        },
        "end": {
          "line": 7,
          "column": 55
        }
      }
    },
    {
      "type": {
        "label": ";",
        "beforeExpr": true,
        "startsExpr": false,
        "rightAssociative": false,
        "isLoop": false,
        "isAssign": false,
        "prefix": false,
        "postfix": false,
        "binop": null,
        "updateContext": null
      },
      "start": 158,
      "end": 159,
      "loc": {
        "start": {
          "line": 7,
          "column": 55
        },
        "end": {
          "line": 7,
          "column": 56
        }
      }
    },
    {
      "type": {
        "label": "export",
        "keyword": "export",
        "beforeExpr": false,
        "startsExpr": false,
        "rightAssociative": false,
        "isLoop": false,
        "isAssign": false,
        "prefix": false,
        "postfix": false,
        "binop": null,
        "updateContext": null
      },
      "value": "export",
      "start": 160,
      "end": 166,
      "loc": {
        "start": {
          "line": 8,
          "column": 0
        },
        "end": {
          "line": 8,
          "column": 6
        }
      }
    },
    {
      "type": {
        "label": "{",
        "beforeExpr": true,
        "startsExpr": true,
        "rightAssociative": false,
        "isLoop": false,
        "isAssign": false,
        "prefix": false,
        "postfix": false,
        "binop": null
      },
      "start": 167,
      "end": 168,
      "loc": {
        "start": {
          "line": 8,
          "column": 7
        },
        "end": {
          "line": 8,
          "column": 8
        }
      }
    },
    {
      "type": {
        "label": "default",
        "keyword": "default",
        "beforeExpr": true,
        "startsExpr": false,
        "rightAssociative": false,
        "isLoop": false,
        "isAssign": false,
        "prefix": false,
        "postfix": false,
        "binop": null,
        "updateContext": null
      },
      "value": "default",
      "start": 168,
      "end": 175,
      "loc": {
        "start": {
          "line": 8,
          "column": 8
        },
        "end": {
          "line": 8,
          "column": 15
        }
      }
    },
    {
      "type": {
        "label": "name",
        "beforeExpr": false,
        "startsExpr": true,
        "rightAssociative": false,
        "isLoop": false,
        "isAssign": false,
        "prefix": false,
        "postfix": false,
        "binop": null
      },
      "value": "as",
      "start": 176,
      "end": 178,
      "loc": {
        "start": {
          "line": 8,
          "column": 16
        },
        "end": {
          "line": 8,
          "column": 18
        }
      }
    },
    {
      "type": {
        "label": "name",
        "beforeExpr": false,
        "startsExpr": true,
        "rightAssociative": false,
        "isLoop": false,
        "isAssign": false,
        "prefix": false,
        "postfix": false,
        "binop": null
      },
      "value": "TimelineBody",
      "start": 179,
      "end": 191,
      "loc": {
        "start": {
          "line": 8,
          "column": 19
        },
        "end": {
          "line": 8,
          "column": 31
        }
      }
    },
    {
      "type": {
        "label": "}",
        "beforeExpr": false,
        "startsExpr": false,
        "rightAssociative": false,
        "isLoop": false,
        "isAssign": false,
        "prefix": false,
        "postfix": false,
        "binop": null
      },
      "start": 191,
      "end": 192,
      "loc": {
        "start": {
          "line": 8,
          "column": 31
        },
        "end": {
          "line": 8,
          "column": 32
        }
      }
    },
    {
      "type": {
        "label": "name",
        "beforeExpr": false,
        "startsExpr": true,
        "rightAssociative": false,
        "isLoop": false,
        "isAssign": false,
        "prefix": false,
        "postfix": false,
        "binop": null
      },
      "value": "from",
      "start": 193,
      "end": 197,
      "loc": {
        "start": {
          "line": 8,
          "column": 33
        },
        "end": {
          "line": 8,
          "column": 37
        }
      }
    },
    {
      "type": {
        "label": "string",
        "beforeExpr": false,
        "startsExpr": true,
        "rightAssociative": false,
        "isLoop": false,
        "isAssign": false,
        "prefix": false,
        "postfix": false,
        "binop": null,
        "updateContext": null
      },
      "value": "./components/body",
      "start": 198,
      "end": 217,
      "loc": {
        "start": {
          "line": 8,
          "column": 38
        },
        "end": {
          "line": 8,
          "column": 57
        }
      }
    },
    {
      "type": {
        "label": ";",
        "beforeExpr": true,
        "startsExpr": false,
        "rightAssociative": false,
        "isLoop": false,
        "isAssign": false,
        "prefix": false,
        "postfix": false,
        "binop": null,
        "updateContext": null
      },
      "start": 217,
      "end": 218,
      "loc": {
        "start": {
          "line": 8,
          "column": 57
        },
        "end": {
          "line": 8,
          "column": 58
        }
      }
    },
    {
      "type": {
        "label": "export",
        "keyword": "export",
        "beforeExpr": false,
        "startsExpr": false,
        "rightAssociative": false,
        "isLoop": false,
        "isAssign": false,
        "prefix": false,
        "postfix": false,
        "binop": null,
        "updateContext": null
      },
      "value": "export",
      "start": 219,
      "end": 225,
      "loc": {
        "start": {
          "line": 9,
          "column": 0
        },
        "end": {
          "line": 9,
          "column": 6
        }
      }
    },
    {
      "type": {
        "label": "{",
        "beforeExpr": true,
        "startsExpr": true,
        "rightAssociative": false,
        "isLoop": false,
        "isAssign": false,
        "prefix": false,
        "postfix": false,
        "binop": null
      },
      "start": 226,
      "end": 227,
      "loc": {
        "start": {
          "line": 9,
          "column": 7
        },
        "end": {
          "line": 9,
          "column": 8
        }
      }
    },
    {
      "type": {
        "label": "default",
        "keyword": "default",
        "beforeExpr": true,
        "startsExpr": false,
        "rightAssociative": false,
        "isLoop": false,
        "isAssign": false,
        "prefix": false,
        "postfix": false,
        "binop": null,
        "updateContext": null
      },
      "value": "default",
      "start": 227,
      "end": 234,
      "loc": {
        "start": {
          "line": 9,
          "column": 8
        },
        "end": {
          "line": 9,
          "column": 15
        }
      }
    },
    {
      "type": {
        "label": "name",
        "beforeExpr": false,
        "startsExpr": true,
        "rightAssociative": false,
        "isLoop": false,
        "isAssign": false,
        "prefix": false,
        "postfix": false,
        "binop": null
      },
      "value": "as",
      "start": 235,
      "end": 237,
      "loc": {
        "start": {
          "line": 9,
          "column": 16
        },
        "end": {
          "line": 9,
          "column": 18
        }
      }
    },
    {
      "type": {
        "label": "name",
        "beforeExpr": false,
        "startsExpr": true,
        "rightAssociative": false,
        "isLoop": false,
        "isAssign": false,
        "prefix": false,
        "postfix": false,
        "binop": null
      },
      "value": "ItemRenderer",
      "start": 238,
      "end": 250,
      "loc": {
        "start": {
          "line": 9,
          "column": 19
        },
        "end": {
          "line": 9,
          "column": 31
        }
      }
    },
    {
      "type": {
        "label": "}",
        "beforeExpr": false,
        "startsExpr": false,
        "rightAssociative": false,
        "isLoop": false,
        "isAssign": false,
        "prefix": false,
        "postfix": false,
        "binop": null
      },
      "start": 250,
      "end": 251,
      "loc": {
        "start": {
          "line": 9,
          "column": 31
        },
        "end": {
          "line": 9,
          "column": 32
        }
      }
    },
    {
      "type": {
        "label": "name",
        "beforeExpr": false,
        "startsExpr": true,
        "rightAssociative": false,
        "isLoop": false,
        "isAssign": false,
        "prefix": false,
        "postfix": false,
        "binop": null
      },
      "value": "from",
      "start": 252,
      "end": 256,
      "loc": {
        "start": {
          "line": 9,
          "column": 33
        },
        "end": {
          "line": 9,
          "column": 37
        }
      }
    },
    {
      "type": {
        "label": "string",
        "beforeExpr": false,
        "startsExpr": true,
        "rightAssociative": false,
        "isLoop": false,
        "isAssign": false,
        "prefix": false,
        "postfix": false,
        "binop": null,
        "updateContext": null
      },
      "value": "./components/ItemRenderer",
      "start": 257,
      "end": 284,
      "loc": {
        "start": {
          "line": 9,
          "column": 38
        },
        "end": {
          "line": 9,
          "column": 65
        }
      }
    },
    {
      "type": {
        "label": ";",
        "beforeExpr": true,
        "startsExpr": false,
        "rightAssociative": false,
        "isLoop": false,
        "isAssign": false,
        "prefix": false,
        "postfix": false,
        "binop": null,
        "updateContext": null
      },
      "start": 284,
      "end": 285,
      "loc": {
        "start": {
          "line": 9,
          "column": 65
        },
        "end": {
          "line": 9,
          "column": 66
        }
      }
    },
    {
      "type": {
        "label": "export",
        "keyword": "export",
        "beforeExpr": false,
        "startsExpr": false,
        "rightAssociative": false,
        "isLoop": false,
        "isAssign": false,
        "prefix": false,
        "postfix": false,
        "binop": null,
        "updateContext": null
      },
      "value": "export",
      "start": 286,
      "end": 292,
      "loc": {
        "start": {
          "line": 10,
          "column": 0
        },
        "end": {
          "line": 10,
          "column": 6
        }
      }
    },
    {
      "type": {
        "label": "{",
        "beforeExpr": true,
        "startsExpr": true,
        "rightAssociative": false,
        "isLoop": false,
        "isAssign": false,
        "prefix": false,
        "postfix": false,
        "binop": null
      },
      "start": 293,
      "end": 294,
      "loc": {
        "start": {
          "line": 10,
          "column": 7
        },
        "end": {
          "line": 10,
          "column": 8
        }
      }
    },
    {
      "type": {
        "label": "name",
        "beforeExpr": false,
        "startsExpr": true,
        "rightAssociative": false,
        "isLoop": false,
        "isAssign": false,
        "prefix": false,
        "postfix": false,
        "binop": null
      },
      "value": "GroupRenderer",
      "start": 294,
      "end": 307,
      "loc": {
        "start": {
          "line": 10,
          "column": 8
        },
        "end": {
          "line": 10,
          "column": 21
        }
      }
    },
    {
      "type": {
        "label": "}",
        "beforeExpr": false,
        "startsExpr": false,
        "rightAssociative": false,
        "isLoop": false,
        "isAssign": false,
        "prefix": false,
        "postfix": false,
        "binop": null
      },
      "start": 307,
      "end": 308,
      "loc": {
        "start": {
          "line": 10,
          "column": 21
        },
        "end": {
          "line": 10,
          "column": 22
        }
      }
    },
    {
      "type": {
        "label": "name",
        "beforeExpr": false,
        "startsExpr": true,
        "rightAssociative": false,
        "isLoop": false,
        "isAssign": false,
        "prefix": false,
        "postfix": false,
        "binop": null
      },
      "value": "from",
      "start": 309,
      "end": 313,
      "loc": {
        "start": {
          "line": 10,
          "column": 23
        },
        "end": {
          "line": 10,
          "column": 27
        }
      }
    },
    {
      "type": {
        "label": "string",
        "beforeExpr": false,
        "startsExpr": true,
        "rightAssociative": false,
        "isLoop": false,
        "isAssign": false,
        "prefix": false,
        "postfix": false,
        "binop": null,
        "updateContext": null
      },
      "value": "./components/GroupRenderer",
      "start": 314,
      "end": 342,
      "loc": {
        "start": {
          "line": 10,
          "column": 28
        },
        "end": {
          "line": 10,
          "column": 56
        }
      }
    },
    {
      "type": {
        "label": ";",
        "beforeExpr": true,
        "startsExpr": false,
        "rightAssociative": false,
        "isLoop": false,
        "isAssign": false,
        "prefix": false,
        "postfix": false,
        "binop": null,
        "updateContext": null
      },
      "start": 342,
      "end": 343,
      "loc": {
        "start": {
          "line": 10,
          "column": 56
        },
        "end": {
          "line": 10,
          "column": 57
        }
      }
    },
    {
      "type": {
        "label": "export",
        "keyword": "export",
        "beforeExpr": false,
        "startsExpr": false,
        "rightAssociative": false,
        "isLoop": false,
        "isAssign": false,
        "prefix": false,
        "postfix": false,
        "binop": null,
        "updateContext": null
      },
      "value": "export",
      "start": 344,
      "end": 350,
      "loc": {
        "start": {
          "line": 11,
          "column": 0
        },
        "end": {
          "line": 11,
          "column": 6
        }
      }
    },
    {
      "type": {
        "label": "{",
        "beforeExpr": true,
        "startsExpr": true,
        "rightAssociative": false,
        "isLoop": false,
        "isAssign": false,
        "prefix": false,
        "postfix": false,
        "binop": null
      },
      "start": 351,
      "end": 352,
      "loc": {
        "start": {
          "line": 11,
          "column": 7
        },
        "end": {
          "line": 11,
          "column": 8
        }
      }
    },
    {
      "type": {
        "label": "name",
        "beforeExpr": false,
        "startsExpr": true,
        "rightAssociative": false,
        "isLoop": false,
        "isAssign": false,
        "prefix": false,
        "postfix": false,
        "binop": null
      },
      "value": "ColumnHeaderRenderer",
      "start": 352,
      "end": 372,
      "loc": {
        "start": {
          "line": 11,
          "column": 8
        },
        "end": {
          "line": 11,
          "column": 28
        }
      }
    },
    {
      "type": {
        "label": "}",
        "beforeExpr": false,
        "startsExpr": false,
        "rightAssociative": false,
        "isLoop": false,
        "isAssign": false,
        "prefix": false,
        "postfix": false,
        "binop": null
      },
      "start": 372,
      "end": 373,
      "loc": {
        "start": {
          "line": 11,
          "column": 28
        },
        "end": {
          "line": 11,
          "column": 29
        }
      }
    },
    {
      "type": {
        "label": "name",
        "beforeExpr": false,
        "startsExpr": true,
        "rightAssociative": false,
        "isLoop": false,
        "isAssign": false,
        "prefix": false,
        "postfix": false,
        "binop": null
      },
      "value": "from",
      "start": 374,
      "end": 378,
      "loc": {
        "start": {
          "line": 11,
          "column": 30
        },
        "end": {
          "line": 11,
          "column": 34
        }
      }
    },
    {
      "type": {
        "label": "string",
        "beforeExpr": false,
        "startsExpr": true,
        "rightAssociative": false,
        "isLoop": false,
        "isAssign": false,
        "prefix": false,
        "postfix": false,
        "binop": null,
        "updateContext": null
      },
      "value": "./components/ColumnRenderer",
      "start": 379,
      "end": 408,
      "loc": {
        "start": {
          "line": 11,
          "column": 35
        },
        "end": {
          "line": 11,
          "column": 64
        }
      }
    },
    {
      "type": {
        "label": ";",
        "beforeExpr": true,
        "startsExpr": false,
        "rightAssociative": false,
        "isLoop": false,
        "isAssign": false,
        "prefix": false,
        "postfix": false,
        "binop": null,
        "updateContext": null
      },
      "start": 408,
      "end": 409,
      "loc": {
        "start": {
          "line": 11,
          "column": 64
        },
        "end": {
          "line": 11,
          "column": 65
        }
      }
    },
    {
      "type": {
        "label": "export",
        "keyword": "export",
        "beforeExpr": false,
        "startsExpr": false,
        "rightAssociative": false,
        "isLoop": false,
        "isAssign": false,
        "prefix": false,
        "postfix": false,
        "binop": null,
        "updateContext": null
      },
      "value": "export",
      "start": 410,
      "end": 416,
      "loc": {
        "start": {
          "line": 12,
          "column": 0
        },
        "end": {
          "line": 12,
          "column": 6
        }
      }
    },
    {
      "type": {
        "label": "{",
        "beforeExpr": true,
        "startsExpr": true,
        "rightAssociative": false,
        "isLoop": false,
        "isAssign": false,
        "prefix": false,
        "postfix": false,
        "binop": null
      },
      "start": 417,
      "end": 418,
      "loc": {
        "start": {
          "line": 12,
          "column": 7
        },
        "end": {
          "line": 12,
          "column": 8
        }
      }
    },
    {
      "type": {
        "label": "default",
        "keyword": "default",
        "beforeExpr": true,
        "startsExpr": false,
        "rightAssociative": false,
        "isLoop": false,
        "isAssign": false,
        "prefix": false,
        "postfix": false,
        "binop": null,
        "updateContext": null
      },
      "value": "default",
      "start": 418,
      "end": 425,
      "loc": {
        "start": {
          "line": 12,
          "column": 8
        },
        "end": {
          "line": 12,
          "column": 15
        }
      }
    },
    {
      "type": {
        "label": "name",
        "beforeExpr": false,
        "startsExpr": true,
        "rightAssociative": false,
        "isLoop": false,
        "isAssign": false,
        "prefix": false,
        "postfix": false,
        "binop": null
      },
      "value": "as",
      "start": 426,
      "end": 428,
      "loc": {
        "start": {
          "line": 12,
          "column": 16
        },
        "end": {
          "line": 12,
          "column": 18
        }
      }
    },
    {
      "type": {
        "label": "name",
        "beforeExpr": false,
        "startsExpr": true,
        "rightAssociative": false,
        "isLoop": false,
        "isAssign": false,
        "prefix": false,
        "postfix": false,
        "binop": null
      },
      "value": "Marker",
      "start": 429,
      "end": 435,
      "loc": {
        "start": {
          "line": 12,
          "column": 19
        },
        "end": {
          "line": 12,
          "column": 25
        }
      }
    },
    {
      "type": {
        "label": "}",
        "beforeExpr": false,
        "startsExpr": false,
        "rightAssociative": false,
        "isLoop": false,
        "isAssign": false,
        "prefix": false,
        "postfix": false,
        "binop": null
      },
      "start": 435,
      "end": 436,
      "loc": {
        "start": {
          "line": 12,
          "column": 25
        },
        "end": {
          "line": 12,
          "column": 26
        }
      }
    },
    {
      "type": {
        "label": "name",
        "beforeExpr": false,
        "startsExpr": true,
        "rightAssociative": false,
        "isLoop": false,
        "isAssign": false,
        "prefix": false,
        "postfix": false,
        "binop": null
      },
      "value": "from",
      "start": 437,
      "end": 441,
      "loc": {
        "start": {
          "line": 12,
          "column": 27
        },
        "end": {
          "line": 12,
          "column": 31
        }
      }
    },
    {
      "type": {
        "label": "string",
        "beforeExpr": false,
        "startsExpr": true,
        "rightAssociative": false,
        "isLoop": false,
        "isAssign": false,
        "prefix": false,
        "postfix": false,
        "binop": null,
        "updateContext": null
      },
      "value": "./components/marker",
      "start": 442,
      "end": 463,
      "loc": {
        "start": {
          "line": 12,
          "column": 32
        },
        "end": {
          "line": 12,
          "column": 53
        }
      }
    },
    {
      "type": {
        "label": ";",
        "beforeExpr": true,
        "startsExpr": false,
        "rightAssociative": false,
        "isLoop": false,
        "isAssign": false,
        "prefix": false,
        "postfix": false,
        "binop": null,
        "updateContext": null
      },
      "start": 463,
      "end": 464,
      "loc": {
        "start": {
          "line": 12,
          "column": 53
        },
        "end": {
          "line": 12,
          "column": 54
        }
      }
    },
    {
      "type": {
        "label": "export",
        "keyword": "export",
        "beforeExpr": false,
        "startsExpr": false,
        "rightAssociative": false,
        "isLoop": false,
        "isAssign": false,
        "prefix": false,
        "postfix": false,
        "binop": null,
        "updateContext": null
      },
      "value": "export",
      "start": 465,
      "end": 471,
      "loc": {
        "start": {
          "line": 13,
          "column": 0
        },
        "end": {
          "line": 13,
          "column": 6
        }
      }
    },
    {
      "type": {
        "label": "{",
        "beforeExpr": true,
        "startsExpr": true,
        "rightAssociative": false,
        "isLoop": false,
        "isAssign": false,
        "prefix": false,
        "postfix": false,
        "binop": null
      },
      "start": 472,
      "end": 473,
      "loc": {
        "start": {
          "line": 13,
          "column": 7
        },
        "end": {
          "line": 13,
          "column": 8
        }
      }
    },
    {
      "type": {
        "label": "default",
        "keyword": "default",
        "beforeExpr": true,
        "startsExpr": false,
        "rightAssociative": false,
        "isLoop": false,
        "isAssign": false,
        "prefix": false,
        "postfix": false,
        "binop": null,
        "updateContext": null
      },
      "value": "default",
      "start": 473,
      "end": 480,
      "loc": {
        "start": {
          "line": 13,
          "column": 8
        },
        "end": {
          "line": 13,
          "column": 15
        }
      }
    },
    {
      "type": {
        "label": "name",
        "beforeExpr": false,
        "startsExpr": true,
        "rightAssociative": false,
        "isLoop": false,
        "isAssign": false,
        "prefix": false,
        "postfix": false,
        "binop": null
      },
      "value": "as",
      "start": 481,
      "end": 483,
      "loc": {
        "start": {
          "line": 13,
          "column": 16
        },
        "end": {
          "line": 13,
          "column": 18
        }
      }
    },
    {
      "type": {
        "label": "name",
        "beforeExpr": false,
        "startsExpr": true,
        "rightAssociative": false,
        "isLoop": false,
        "isAssign": false,
        "prefix": false,
        "postfix": false,
        "binop": null
      },
      "value": "Selectbox",
      "start": 484,
      "end": 493,
      "loc": {
        "start": {
          "line": 13,
          "column": 19
        },
        "end": {
          "line": 13,
          "column": 28
        }
      }
    },
    {
      "type": {
        "label": "}",
        "beforeExpr": false,
        "startsExpr": false,
        "rightAssociative": false,
        "isLoop": false,
        "isAssign": false,
        "prefix": false,
        "postfix": false,
        "binop": null
      },
      "start": 493,
      "end": 494,
      "loc": {
        "start": {
          "line": 13,
          "column": 28
        },
        "end": {
          "line": 13,
          "column": 29
        }
      }
    },
    {
      "type": {
        "label": "name",
        "beforeExpr": false,
        "startsExpr": true,
        "rightAssociative": false,
        "isLoop": false,
        "isAssign": false,
        "prefix": false,
        "postfix": false,
        "binop": null
      },
      "value": "from",
      "start": 495,
      "end": 499,
      "loc": {
        "start": {
          "line": 13,
          "column": 30
        },
        "end": {
          "line": 13,
          "column": 34
        }
      }
    },
    {
      "type": {
        "label": "string",
        "beforeExpr": false,
        "startsExpr": true,
        "rightAssociative": false,
        "isLoop": false,
        "isAssign": false,
        "prefix": false,
        "postfix": false,
        "binop": null,
        "updateContext": null
      },
      "value": "./components/selector",
      "start": 500,
      "end": 523,
      "loc": {
        "start": {
          "line": 13,
          "column": 35
        },
        "end": {
          "line": 13,
          "column": 58
        }
      }
    },
    {
      "type": {
        "label": ";",
        "beforeExpr": true,
        "startsExpr": false,
        "rightAssociative": false,
        "isLoop": false,
        "isAssign": false,
        "prefix": false,
        "postfix": false,
        "binop": null,
        "updateContext": null
      },
      "start": 523,
      "end": 524,
      "loc": {
        "start": {
          "line": 13,
          "column": 58
        },
        "end": {
          "line": 13,
          "column": 59
        }
      }
    },
    {
      "type": "CommentLine",
      "value": " consts",
      "start": 526,
      "end": 535,
      "loc": {
        "start": {
          "line": 15,
          "column": 0
        },
        "end": {
          "line": 15,
          "column": 9
        }
      }
    },
    {
      "type": {
        "label": "export",
        "keyword": "export",
        "beforeExpr": false,
        "startsExpr": false,
        "rightAssociative": false,
        "isLoop": false,
        "isAssign": false,
        "prefix": false,
        "postfix": false,
        "binop": null,
        "updateContext": null
      },
      "value": "export",
      "start": 536,
      "end": 542,
      "loc": {
        "start": {
          "line": 16,
          "column": 0
        },
        "end": {
          "line": 16,
          "column": 6
        }
      }
    },
    {
      "type": {
        "label": "{",
        "beforeExpr": true,
        "startsExpr": true,
        "rightAssociative": false,
        "isLoop": false,
        "isAssign": false,
        "prefix": false,
        "postfix": false,
        "binop": null
      },
      "start": 543,
      "end": 544,
      "loc": {
        "start": {
          "line": 16,
          "column": 7
        },
        "end": {
          "line": 16,
          "column": 8
        }
      }
    },
    {
      "type": {
        "label": "name",
        "beforeExpr": false,
        "startsExpr": true,
        "rightAssociative": false,
        "isLoop": false,
        "isAssign": false,
        "prefix": false,
        "postfix": false,
        "binop": null
      },
      "value": "timebarFormat",
      "start": 544,
      "end": 557,
      "loc": {
        "start": {
          "line": 16,
          "column": 8
        },
        "end": {
          "line": 16,
          "column": 21
        }
      }
    },
    {
      "type": {
        "label": "}",
        "beforeExpr": false,
        "startsExpr": false,
        "rightAssociative": false,
        "isLoop": false,
        "isAssign": false,
        "prefix": false,
        "postfix": false,
        "binop": null
      },
      "start": 557,
      "end": 558,
      "loc": {
        "start": {
          "line": 16,
          "column": 21
        },
        "end": {
          "line": 16,
          "column": 22
        }
      }
    },
    {
      "type": {
        "label": "name",
        "beforeExpr": false,
        "startsExpr": true,
        "rightAssociative": false,
        "isLoop": false,
        "isAssign": false,
        "prefix": false,
        "postfix": false,
        "binop": null
      },
      "value": "from",
      "start": 559,
      "end": 563,
      "loc": {
        "start": {
          "line": 16,
          "column": 23
        },
        "end": {
          "line": 16,
          "column": 27
        }
      }
    },
    {
      "type": {
        "label": "string",
        "beforeExpr": false,
        "startsExpr": true,
        "rightAssociative": false,
        "isLoop": false,
        "isAssign": false,
        "prefix": false,
        "postfix": false,
        "binop": null,
        "updateContext": null
      },
      "value": "./consts/timebarConsts",
      "start": 564,
      "end": 588,
      "loc": {
        "start": {
          "line": 16,
          "column": 28
        },
        "end": {
          "line": 16,
          "column": 52
        }
      }
    },
    {
      "type": {
        "label": ";",
        "beforeExpr": true,
        "startsExpr": false,
        "rightAssociative": false,
        "isLoop": false,
        "isAssign": false,
        "prefix": false,
        "postfix": false,
        "binop": null,
        "updateContext": null
      },
      "start": 588,
      "end": 589,
      "loc": {
        "start": {
          "line": 16,
          "column": 52
        },
        "end": {
          "line": 16,
          "column": 53
        }
      }
    },
    {
      "type": "CommentLine",
      "value": " utils",
      "start": 591,
      "end": 599,
      "loc": {
        "start": {
          "line": 18,
          "column": 0
        },
        "end": {
          "line": 18,
          "column": 8
        }
      }
    },
    {
      "type": {
        "label": "export",
        "keyword": "export",
        "beforeExpr": false,
        "startsExpr": false,
        "rightAssociative": false,
        "isLoop": false,
        "isAssign": false,
        "prefix": false,
        "postfix": false,
        "binop": null,
        "updateContext": null
      },
      "value": "export",
      "start": 600,
      "end": 606,
      "loc": {
        "start": {
          "line": 19,
          "column": 0
        },
        "end": {
          "line": 19,
          "column": 6
        }
      }
    },
    {
      "type": {
        "label": "*",
        "beforeExpr": true,
        "startsExpr": false,
        "rightAssociative": false,
        "isLoop": false,
        "isAssign": false,
        "prefix": false,
        "postfix": false,
        "binop": 10,
        "updateContext": null
      },
      "value": "*",
      "start": 607,
      "end": 608,
      "loc": {
        "start": {
          "line": 19,
          "column": 7
        },
        "end": {
          "line": 19,
          "column": 8
        }
      }
    },
    {
      "type": {
        "label": "name",
        "beforeExpr": false,
        "startsExpr": true,
        "rightAssociative": false,
        "isLoop": false,
        "isAssign": false,
        "prefix": false,
        "postfix": false,
        "binop": null
      },
      "value": "from",
      "start": 609,
      "end": 613,
      "loc": {
        "start": {
          "line": 19,
          "column": 9
        },
        "end": {
          "line": 19,
          "column": 13
        }
      }
    },
    {
      "type": {
        "label": "string",
        "beforeExpr": false,
        "startsExpr": true,
        "rightAssociative": false,
        "isLoop": false,
        "isAssign": false,
        "prefix": false,
        "postfix": false,
        "binop": null,
        "updateContext": null
      },
      "value": "./utils/commonUtils",
      "start": 614,
      "end": 635,
      "loc": {
        "start": {
          "line": 19,
          "column": 14
        },
        "end": {
          "line": 19,
          "column": 35
        }
      }
    },
    {
      "type": {
        "label": ";",
        "beforeExpr": true,
        "startsExpr": false,
        "rightAssociative": false,
        "isLoop": false,
        "isAssign": false,
        "prefix": false,
        "postfix": false,
        "binop": null,
        "updateContext": null
      },
      "start": 635,
      "end": 636,
      "loc": {
        "start": {
          "line": 19,
          "column": 35
        },
        "end": {
          "line": 19,
          "column": 36
        }
      }
    },
    {
      "type": {
        "label": "export",
        "keyword": "export",
        "beforeExpr": false,
        "startsExpr": false,
        "rightAssociative": false,
        "isLoop": false,
        "isAssign": false,
        "prefix": false,
        "postfix": false,
        "binop": null,
        "updateContext": null
      },
      "value": "export",
      "start": 637,
      "end": 643,
      "loc": {
        "start": {
          "line": 20,
          "column": 0
        },
        "end": {
          "line": 20,
          "column": 6
        }
      }
    },
    {
      "type": {
        "label": "*",
        "beforeExpr": true,
        "startsExpr": false,
        "rightAssociative": false,
        "isLoop": false,
        "isAssign": false,
        "prefix": false,
        "postfix": false,
        "binop": 10,
        "updateContext": null
      },
      "value": "*",
      "start": 644,
      "end": 645,
      "loc": {
        "start": {
          "line": 20,
          "column": 7
        },
        "end": {
          "line": 20,
          "column": 8
        }
      }
    },
    {
      "type": {
        "label": "name",
        "beforeExpr": false,
        "startsExpr": true,
        "rightAssociative": false,
        "isLoop": false,
        "isAssign": false,
        "prefix": false,
        "postfix": false,
        "binop": null
      },
      "value": "from",
      "start": 646,
      "end": 650,
      "loc": {
        "start": {
          "line": 20,
          "column": 9
        },
        "end": {
          "line": 20,
          "column": 13
        }
      }
    },
    {
      "type": {
        "label": "string",
        "beforeExpr": false,
        "startsExpr": true,
        "rightAssociative": false,
        "isLoop": false,
        "isAssign": false,
        "prefix": false,
        "postfix": false,
        "binop": null,
        "updateContext": null
      },
      "value": "./utils/itemUtils",
      "start": 651,
      "end": 670,
      "loc": {
        "start": {
          "line": 20,
          "column": 14
        },
        "end": {
          "line": 20,
          "column": 33
        }
      }
    },
    {
      "type": {
        "label": ";",
        "beforeExpr": true,
        "startsExpr": false,
        "rightAssociative": false,
        "isLoop": false,
        "isAssign": false,
        "prefix": false,
        "postfix": false,
        "binop": null,
        "updateContext": null
      },
      "start": 670,
      "end": 671,
      "loc": {
        "start": {
          "line": 20,
          "column": 33
        },
        "end": {
          "line": 20,
          "column": 34
        }
      }
    },
    {
      "type": {
        "label": "export",
        "keyword": "export",
        "beforeExpr": false,
        "startsExpr": false,
        "rightAssociative": false,
        "isLoop": false,
        "isAssign": false,
        "prefix": false,
        "postfix": false,
        "binop": null,
        "updateContext": null
      },
      "value": "export",
      "start": 672,
      "end": 678,
      "loc": {
        "start": {
          "line": 21,
          "column": 0
        },
        "end": {
          "line": 21,
          "column": 6
        }
      }
    },
    {
      "type": {
        "label": "*",
        "beforeExpr": true,
        "startsExpr": false,
        "rightAssociative": false,
        "isLoop": false,
        "isAssign": false,
        "prefix": false,
        "postfix": false,
        "binop": 10,
        "updateContext": null
      },
      "value": "*",
      "start": 679,
      "end": 680,
      "loc": {
        "start": {
          "line": 21,
          "column": 7
        },
        "end": {
          "line": 21,
          "column": 8
        }
      }
    },
    {
      "type": {
        "label": "name",
        "beforeExpr": false,
        "startsExpr": true,
        "rightAssociative": false,
        "isLoop": false,
        "isAssign": false,
        "prefix": false,
        "postfix": false,
        "binop": null
      },
      "value": "from",
      "start": 681,
      "end": 685,
      "loc": {
        "start": {
          "line": 21,
          "column": 9
        },
        "end": {
          "line": 21,
          "column": 13
        }
      }
    },
    {
      "type": {
        "label": "string",
        "beforeExpr": false,
        "startsExpr": true,
        "rightAssociative": false,
        "isLoop": false,
        "isAssign": false,
        "prefix": false,
        "postfix": false,
        "binop": null,
        "updateContext": null
      },
      "value": "./utils/timeUtils",
      "start": 686,
      "end": 705,
      "loc": {
        "start": {
          "line": 21,
          "column": 14
        },
        "end": {
          "line": 21,
          "column": 33
        }
      }
    },
    {
      "type": {
        "label": ";",
        "beforeExpr": true,
        "startsExpr": false,
        "rightAssociative": false,
        "isLoop": false,
        "isAssign": false,
        "prefix": false,
        "postfix": false,
        "binop": null,
        "updateContext": null
      },
      "start": 705,
      "end": 706,
      "loc": {
        "start": {
          "line": 21,
          "column": 33
        },
        "end": {
          "line": 21,
          "column": 34
        }
      }
    },
    {
      "type": {
        "label": "eof",
        "beforeExpr": false,
        "startsExpr": false,
        "rightAssociative": false,
        "isLoop": false,
        "isAssign": false,
        "prefix": false,
        "postfix": false,
        "binop": null,
        "updateContext": null
      },
      "start": 707,
      "end": 707,
      "loc": {
        "start": {
          "line": 22,
          "column": 0
        },
        "end": {
          "line": 22,
          "column": 0
        }
      }
    }
  ]
}